robocop/__init__.py
robocop/__main__.py
robocop/config.py
robocop/exceptions.py
robocop/files.py
robocop/migrate_config.py
robocop/run.py
robocop/formatter/__init__.py
robocop/formatter/disablers.py
robocop/formatter/runner.py
robocop/formatter/skip.py
robocop/formatter/formatters/AddMissingEnd.py
robocop/formatter/formatters/AlignKeywordsSection.py
robocop/formatter/formatters/AlignSettingsSection.py
robocop/formatter/formatters/AlignTemplatedTestCases.py
robocop/formatter/formatters/AlignTestCasesSection.py
robocop/formatter/formatters/AlignVariablesSection.py
robocop/formatter/formatters/DiscardEmptySections.py
robocop/formatter/formatters/GenerateDocumentation.py
robocop/formatter/formatters/IndentNestedKeywords.py
robocop/formatter/formatters/InlineIf.py
robocop/formatter/formatters/MergeAndOrderSections.py
robocop/formatter/formatters/NormalizeAssignments.py
robocop/formatter/formatters/NormalizeComments.py
robocop/formatter/formatters/NormalizeNewLines.py
robocop/formatter/formatters/NormalizeSectionHeaderName.py
robocop/formatter/formatters/NormalizeSeparators.py
robocop/formatter/formatters/NormalizeSettingName.py
robocop/formatter/formatters/NormalizeTags.py
robocop/formatter/formatters/OrderSettings.py
robocop/formatter/formatters/OrderSettingsSection.py
robocop/formatter/formatters/OrderTags.py
robocop/formatter/formatters/RemoveEmptySettings.py
robocop/formatter/formatters/RenameKeywords.py
robocop/formatter/formatters/RenameTestCases.py
robocop/formatter/formatters/RenameVariables.py
robocop/formatter/formatters/ReplaceBreakContinue.py
robocop/formatter/formatters/ReplaceEmptyValues.py
robocop/formatter/formatters/ReplaceReturns.py
robocop/formatter/formatters/ReplaceRunKeywordIf.py
robocop/formatter/formatters/ReplaceWithVAR.py
robocop/formatter/formatters/SmartSortKeywords.py
robocop/formatter/formatters/SplitTooLongLine.py
robocop/formatter/formatters/Translate.py
robocop/formatter/formatters/__init__.py
robotframework_robocop-7.0.0.dist-info/METADATA
robotframework_robocop-7.0.0.dist-info/WHEEL
robotframework_robocop-7.0.0.dist-info/entry_points.txt
robotframework_robocop-7.0.0.dist-info/licenses/LICENSE
robotframework_robocop-7.0.0.dist-info/RECORD
