Metadata-Version: 2.4
Name: robotframework-robocop
Version: 7.0.0
Summary: Static code analysis tool (linter) and code formatter for Robot Framework
Project-URL: Bug tracker, https://github.com/MarketSquare/robotframework-robocop/issues
Project-URL: Source code, https://github.com/MarketSquare/robotframework-robocop
Project-URL: Documentation, https://robocop.dev/
Project-URL: Homepage, https://robocop.dev/
Author-email: Bartlomiej Hirsz <bartek.hirsz@gmail.com>, Mateusz Nojek <matnojek@gmail.com>
Maintainer-email: Bartlomiej Hirsz <bartek.hirsz@gmail.com>
License-File: LICENSE
Keywords: automation,formatter,formatting,linter,qa,robotframework,testautomation,testing
Classifier: Development Status :: 5 - Production/Stable
Classifier: Framework :: Robot Framework
Classifier: Framework :: Robot Framework :: Tool
Classifier: Intended Audience :: Developers
Classifier: License :: OSI Approved :: Apache Software License
Classifier: Operating System :: OS Independent
Classifier: Programming Language :: Python
Classifier: Programming Language :: Python :: 3.9
Classifier: Programming Language :: Python :: 3.10
Classifier: Programming Language :: Python :: 3.11
Classifier: Programming Language :: Python :: 3.12
Classifier: Programming Language :: Python :: 3.13
Classifier: Programming Language :: Python :: 3.14
Classifier: Topic :: Software Development :: Quality Assurance
Classifier: Topic :: Software Development :: Testing
Classifier: Topic :: Utilities
Requires-Python: >=3.9
Requires-Dist: jinja2>=3.1.4
Requires-Dist: pathspec>=0.12
Requires-Dist: platformdirs>=4.3
Requires-Dist: pytz>=2022.7
Requires-Dist: rich>=10.11.0
Requires-Dist: robotframework<7.5,>=4.0
Requires-Dist: tomli-w>=1.0
Requires-Dist: tomli==2.2.1; python_version < '3.11'
Requires-Dist: typer-slim>=0.12.5
